conteneurs/__init__.py
conteneurs/dictionnaire_ordonné.py
conteneurs/tableau.py
conteneurs-2.1.2.data/data/Documentation technique conteneurs.pdf
tests/__init__.py
tests/tests_dictionnaire_ordonné.py
tests/tests_tableau.py
conteneurs-2.1.2.dist-info/METADATA
conteneurs-2.1.2.dist-info/WHEEL
conteneurs-2.1.2.dist-info/top_level.txt
conteneurs-2.1.2.dist-info/RECORD
