Metadata-Version: 2.1
Name: conteneurs
Version: 2.1.2
Summary: Le package conteneurs définit des conteneurs supplémentaires.
Home-page: UNKNOWN
Author: Cyprien BONTRON
Author-email: c.b.e.python@gmail.com
Maintainer: Cyprien BONTRON
Maintainer-email: c.b.e.python@gmail.com
License: CC-BY-NC (Creative Commons, attribution et non commerciale).
Download-URL: https://pypi.org/project/conteneurs/
Platform: UNKNOWN
Classifier: Programming Language :: Python :: 3.7
Classifier: Programming Language :: Python :: 3.8
Classifier: Programming Language :: Python :: 3.9
Classifier: Natural Language :: French
Classifier: Intended Audience :: Developers
Classifier: Intended Audience :: Science/Research
Classifier: Intended Audience :: Information Technology
Classifier: License :: Free for non-commercial use
Requires-Python: >=3.7
Requires-Dist: outils-de-controles (>=2.4.9)
